Metadata-Version: 2.1
Name: movinadd
Version: 1.0.0
Summary: Trial Add library
License-File: LICENSE.txt
